{
 "aggregate_function_based_on": "",
 "creation": "2024-02-19 15:58:42.521866",
 "docstatus": 0,
 "doctype": "Number Card",
 "document_type": "Donation",
 "dynamic_filters_json": "{}",
 "filters_json": "{\"donor\":\"\",\"range\":\"Monthly\"}",
 "function": "Count",
 "idx": 0,
 "is_public": 0,
 "is_standard": 1,
 "label": "Total Donations",
 "modified": "2024-02-19 16:46:51.458185",
 "modified_by": "Administrator",
 "module": "Donor Management",
 "name": "Total Donations",
 "owner": "Administrator",
 "parent_document_type": "",
 "report_field": "tranche_amount",
 "report_function": "Sum",
 "report_name": "Donation Report",
 "show_percentage_stats": 1,
 "stats_time_interval": "Monthly",
 "type": "Report"
}